{
  "$schema": "https://raw.githubusercontent.com/electron-userland/electron-builder/master/packages/app-builder-lib/scheme.json",
  "appId": "dev.carlosd.crocdesktop",
  "asar": true,
  "productName": "Croc Desktop",
  "compression": "maximum",
  "removePackageScripts": true,
  "directories": {
    "output": "dist-release",
    "buildResources": "build"
  },
  "files": [
    "dist",
    "dist-electron"
  ],
  // node-pty ships a native .node binary; keep it unpacked so it loads from asar.
  "asarUnpack": [
    "**/node_modules/node-pty/**"
  ],
  "mac": {
    "target": [
      {
        "target": "dmg",
        "arch": [
          "x64",
          "arm64"
        ]
      },
      {
        "target": "zip",
        "arch": [
          "x64",
          "arm64"
        ]
      }
    ],
    "artifactName": "${productName}-Mac-${version}-${arch}.${ext}",
    "category": "public.app-category.utilities"
  },
  "win": {
    "target": [
      {
        "target": "nsis",
        "arch": [
          "x64"
        ]
      }
    ],
    "artifactName": "${productName}-Windows-${version}-Setup.${ext}"
  },
  "linux": {
    "target": [
      "AppImage",
      "deb"
    ],
    "category": "Utility",
    "artifactName": "${productName}-Linux-${version}-${arch}.${ext}"
  },
  "nsis": {
    "oneClick": false,
    "perMachine": false,
    "allowToChangeInstallationDirectory": true,
    "createDesktopShortcut": true,
    "createStartMenuShortcut": true,
    "runAfterFinish": true
  }
}